[{"filename":"00.jpg","seg_id":34325,"content":"Move forward"},{"filename":"01.jpg","content":"Move forward"},{"filename":"02.jpg","seg_id":34327,"content":"Move forward & turn right"},{"filename":"03.jpg","seg_id":34329,"content":"Move forward & turn right"},{"filename":"04.jpg","seg_id":34330,"content":"Take escalator to Level 2"},{"filename":"05.jpg","seg_id":34331,"content":"Take escalator to Level 2"},{"filename":"06.jpg","seg_id":34332,"content":"Move forward"},{"filename":"07.jpg","seg_id":34334,"content":"Move forward"},{"filename":"08.jpg","seg_id":34335,"content":"Move forward"},{"filename":"09.jpg","content":"Move forward"},{"filename":"10.jpg","seg_id":34336,"content":"Move forward"},{"filename":"11.jpg","seg_id":34338,"content":"Move forward & turn right"},{"filename":"12.jpg","seg_id":34339,"content":"Move forward & turn left"},{"filename":"13.jpg","seg_id":34341,"content":"Turn right"},{"filename":"14.jpg","seg_id":34342,"content":"Move forward"},{"filename":"15.jpg","seg_id":34343,"content":"You have reached Specialist Clinic A"}]
